ibloom.cpython-38-darwin.so
tests/__init__.py
tests/test_accuracy.py
ibloom-0.0.2.1.1.dist-info/LICENSE
ibloom-0.0.2.1.1.dist-info/METADATA
ibloom-0.0.2.1.1.dist-info/WHEEL
ibloom-0.0.2.1.1.dist-info/top_level.txt
ibloom-0.0.2.1.1.dist-info/RECORD
